{"_type":"export","__export_format":4,"__export_date":"2020-04-21T18:04:24.429Z","__export_source":"insomnia.desktop.app:v7.1.1","resources":[{"_id":"req_061bfa1db45c4b90a50d76c37978422d","authentication":{"token":"{{ token  }}","type":"bearer"},"body":{},"created":1587491391287,"description":"","headers":[],"isPrivate":false,"metaSortKey":-1587491391287,"method":"GET","modified":1587491425537,"name":"list","parameters":[],"parentId":"fld_8cacd6da405947b3aabd42f580889784","settingDisableRenderRequestBody":false,"settingEncodeUrl":true,"settingFollowRedirects":"global","settingRebuildPath":true,"settingSendCookies":true,"settingStoreCookies":true,"url":"{{ baseURL  }}/notifications","_type":"request"},{"_id":"fld_8cacd6da405947b3aabd42f580889784","created":1587491381160,"description":"","environment":{},"environmentPropertyOrder":null,"metaSortKey":-1587491381160,"modified":1587491381160,"name":"notification","parentId":"wrk_31b0b95dd0db41dcbbd866132bb9e4fd","_type":"request_group"},{"_id":"wrk_31b0b95dd0db41dcbbd866132bb9e4fd","created":1586215246546,"description":"","modified":1586215246546,"name":"Insomnia","parentId":null,"_type":"workspace"},{"_id":"req_b454358ec84e4e5796f8895cfe3e0c1e","authentication":{"token":"{{ token  }}","type":"bearer"},"body":{},"created":1587491486936,"description":"","headers":[],"isPrivate":false,"metaSortKey":-1587491207187,"method":"PUT","modified":1587491501490,"name":"update","parameters":[],"parentId":"fld_8cacd6da405947b3aabd42f580889784","settingDisableRenderRequestBody":false,"settingEncodeUrl":true,"settingFollowRedirects":"global","settingRebuildPath":true,"settingSendCookies":true,"settingStoreCookies":true,"url":"{{ baseURL  }}/notifications/5e9f301d28ceee1c4cdf1799","_type":"request"},{"_id":"req_60af2b42922945428270fde6d5d8bca3","authentication":{"token":"{{ token  }}","type":"bearer"},"body":{},"created":1587491023087,"description":"","headers":[],"isPrivate":false,"metaSortKey":-1587491023087,"method":"GET","modified":1587491265319,"name":"schedule","parameters":[{"description":"","id":"pair_4a97ef9b17bc441a987a0c15be6b22a8","name":"date","value":"2020-04-22T00:00:00-03:00"}],"parentId":"fld_5137819857e442fd86418dc08254b053","settingDisableRenderRequestBody":false,"settingEncodeUrl":true,"settingFollowRedirects":"global","settingRebuildPath":true,"settingSendCookies":true,"settingStoreCookies":true,"url":"{{ baseURL  }}/schedule","_type":"request"},{"_id":"fld_5137819857e442fd86418dc08254b053","created":1587491201032,"description":"","environment":{},"environmentPropertyOrder":null,"metaSortKey":-1587491201032,"modified":1587491201032,"name":"schedule","parentId":"wrk_31b0b95dd0db41dcbbd866132bb9e4fd","_type":"request_group"},{"_id":"req_f69b6d4983bd4befb9b05d149feca2ea","authentication":{"token":"{{ token  }}","type":"bearer"},"body":{},"created":1587487349911,"description":"","headers":[],"isPrivate":false,"metaSortKey":-1587487349911,"method":"GET","modified":1587487381285,"name":"index","parameters":[],"parentId":"fld_d2069fe526d540ed87b5f62c31688737","settingDisableRenderRequestBody":false,"settingEncodeUrl":true,"settingFollowRedirects":"global","settingRebuildPath":true,"settingSendCookies":true,"settingStoreCookies":true,"url":"{{ baseURL  }}/providers","_type":"request"},{"_id":"fld_d2069fe526d540ed87b5f62c31688737","created":1587487337062,"description":"","environment":{},"environmentPropertyOrder":null,"metaSortKey":-1587487337062,"modified":1587487337062,"name":"provider","parentId":"wrk_31b0b95dd0db41dcbbd866132bb9e4fd","_type":"request_group"},{"_id":"req_bef81ca81afe419b9090c84d63a2dd4a","authentication":{"token":"{{ token  }}","type":"bearer"},"body":{"mimeType":"multipart/form-data","params":[{"description":"","fileName":"C:\\Users\\mauric222838\\Downloads\\um.jpeg","id":"pair_dcfb51f5be4144b28ce0dd9e8e5ae138","name":"file","type":"file","value":""}]},"created":1587486376955,"description":"","headers":[{"id":"pair_0ad9f81f346c4ccc8b213d91ae8b4747","name":"Content-Type","value":"multipart/form-data"}],"isPrivate":false,"metaSortKey":-1587486376955,"method":"POST","modified":1587486882123,"name":"create","parameters":[],"parentId":"fld_e15d7dcc32d54c43b64d13acd7675bce","settingDisableRenderRequestBody":false,"settingEncodeUrl":true,"settingFollowRedirects":"global","settingRebuildPath":true,"settingSendCookies":true,"settingStoreCookies":true,"url":"{{ baseURL  }}/files","_type":"request"},{"_id":"fld_e15d7dcc32d54c43b64d13acd7675bce","created":1587486346292,"description":"","environment":{},"environmentPropertyOrder":null,"metaSortKey":-1587486346292,"modified":1587486346292,"name":"Files","parentId":"wrk_31b0b95dd0db41dcbbd866132bb9e4fd","_type":"request_group"},{"_id":"req_17823a922cee4368b9835df79c592390","authentication":{},"body":{"mimeType":"application/json","text":"{\n\t\"email\": \"mau@mau.com\",\n\t\"password\": \"123456\"\n}"},"created":1587479611916,"description":"","headers":[{"id":"pair_21b893eada964b2983b5175ed4b0c67c","name":"Content-Type","value":"application/json"}],"isPrivate":false,"metaSortKey":-1587479611916,"method":"POST","modified":1587488011724,"name":"create","parameters":[],"parentId":"fld_712411715e244e0c936dff11cfa5709d","settingDisableRenderRequestBody":false,"settingEncodeUrl":true,"settingFollowRedirects":"global","settingRebuildPath":true,"settingSendCookies":true,"settingStoreCookies":true,"url":"{{ baseURL  }}/sessions","_type":"request"},{"_id":"fld_712411715e244e0c936dff11cfa5709d","created":1587479591789,"description":"","environment":{},"environmentPropertyOrder":null,"metaSortKey":-1587479591789,"modified":1587479591789,"name":"sessions","parentId":"wrk_31b0b95dd0db41dcbbd866132bb9e4fd","_type":"request_group"},{"_id":"req_8ec8ae7aa02545b7b7d631c3bc24826c","authentication":{},"body":{"mimeType":"application/json","text":"{\n\t\"name\": \"teste\",\n\t\"email\": \"t@t.com\",\n\t\"password\": \"123456\"\n\t\n}"},"created":1587479360692,"description":"","headers":[{"id":"pair_378783c1b8dd4371a227d9537ee37529","name":"Content-Type","value":"application/json"}],"isPrivate":false,"metaSortKey":-1587479360692,"method":"POST","modified":1587487747390,"name":"create","parameters":[],"parentId":"fld_ce47757d0d4d4dbd87c5cdf7754e088e","settingDisableRenderRequestBody":false,"settingEncodeUrl":true,"settingFollowRedirects":"global","settingRebuildPath":true,"settingSendCookies":true,"settingStoreCookies":true,"url":"{{ baseURL  }}/users","_type":"request"},{"_id":"fld_ce47757d0d4d4dbd87c5cdf7754e088e","created":1587479350381,"description":"","environment":{},"environmentPropertyOrder":null,"metaSortKey":-1587479350381,"modified":1587479350381,"name":"Users","parentId":"wrk_31b0b95dd0db41dcbbd866132bb9e4fd","_type":"request_group"},{"_id":"req_131cb4592bbc44699db1658b24be6c53","authentication":{"token":"{{ token  }}","type":"bearer"},"body":{"mimeType":"application/json","text":"{\n\t\"name\": \"mauricio bavaresco\",\n\t\"email\": \"mau@mau.com\",\n\t\"oldPassword\": \"1234567\",\n\t\"password\": \"123456\",\n\t\"confirmPassword\": \"123456\",\n\t\"avatar_id\": 1\n}"},"created":1587479705676,"description":"","headers":[{"id":"pair_378783c1b8dd4371a227d9537ee37529","name":"Content-Type","value":"application/json"}],"isPrivate":false,"metaSortKey":-1586888001020,"method":"PUT","modified":1587487729412,"name":"update","parameters":[],"parentId":"fld_ce47757d0d4d4dbd87c5cdf7754e088e","settingDisableRenderRequestBody":false,"settingEncodeUrl":true,"settingFollowRedirects":"global","settingRebuildPath":true,"settingSendCookies":true,"settingStoreCookies":true,"url":"{{ baseURL  }}/users","_type":"request"},{"_id":"req_d2b39c3d3981438a8ae9e899bc5b72d2","authentication":{"token":"{{ token  }}","type":"bearer"},"body":{"mimeType":"application/json","text":"{\n\t\"provider_id\":1,\n\t\"date\": \"2020-04-24T14:00:00-03:00\"\n}"},"created":1586296634560,"description":"","headers":[{"id":"pair_9bcd0130f9754f5583996a7040260f9f","name":"Content-Type","value":"application/json"}],"isPrivate":false,"metaSortKey":-1586296641348,"method":"POST","modified":1587491945565,"name":"create","parameters":[],"parentId":"fld_63fcbe4b676043d58396b133db0d92fd","settingDisableRenderRequestBody":false,"settingEncodeUrl":true,"settingFollowRedirects":"global","settingRebuildPath":true,"settingSendCookies":true,"settingStoreCookies":true,"url":"{{ baseURL  }}/appointments","_type":"request"},{"_id":"fld_63fcbe4b676043d58396b133db0d92fd","created":1586296641398,"description":"","environment":{},"environmentPropertyOrder":null,"metaSortKey":-1586296641398,"modified":1586296641398,"name":"appointments","parentId":"wrk_31b0b95dd0db41dcbbd866132bb9e4fd","_type":"request_group"},{"_id":"req_10869a42ebbc4753ba2c2bf97dbd7716","authentication":{"token":"{{ token  }}","type":"bearer"},"body":{},"created":1587489542123,"description":"","headers":[],"isPrivate":false,"metaSortKey":-1586296641298,"method":"GET","modified":1587491168898,"name":"get","parameters":[{"description":"","id":"pair_3ef26d67e26b4d758049f3e4d6e78f4a","name":"page","value":"1"}],"parentId":"fld_63fcbe4b676043d58396b133db0d92fd","settingDisableRenderRequestBody":false,"settingEncodeUrl":true,"settingFollowRedirects":"global","settingRebuildPath":true,"settingSendCookies":true,"settingStoreCookies":true,"url":"{{ baseURL  }}/appointments","_type":"request"},{"_id":"req_4072fa1f12bc4fdfadfb11fa1e9e8f2a","authentication":{"token":"{{ token  }}","type":"bearer"},"body":{},"created":1587491554520,"description":"","headers":[],"isPrivate":false,"metaSortKey":-1586296641248,"method":"DELETE","modified":1587492191491,"name":"delete","parameters":[{"description":"","id":"pair_3ef26d67e26b4d758049f3e4d6e78f4a","name":"","value":""}],"parentId":"fld_63fcbe4b676043d58396b133db0d92fd","settingDisableRenderRequestBody":false,"settingEncodeUrl":true,"settingFollowRedirects":"global","settingRebuildPath":true,"settingSendCookies":true,"settingStoreCookies":true,"url":"{{ baseURL  }}/appointments/3","_type":"request"},{"_id":"env_c098ce29c3f712171c2c1fdeac00a583250be045","color":null,"created":1586215246601,"data":{"baseURL":"localhost:3333","token":"eyJhbGciOiJIUzI1NiIsInR5cCI6IkpXVCJ9.eyJpZCI6MSwiaWF0IjoxNTg3NDgwMTEzLCJleHAiOjE1ODgwODQ5MTN9.-jVD2b2kmPYWw2k4DixLcUTJRCJTQu5hmh5LQFNrh5g"},"dataPropertyOrder":{"&":["baseURL","token"]},"isPrivate":false,"metaSortKey":1586215246601,"modified":1587486866115,"name":"Base Environment","parentId":"wrk_31b0b95dd0db41dcbbd866132bb9e4fd","_type":"environment"},{"_id":"jar_c098ce29c3f712171c2c1fdeac00a583250be045","cookies":[],"created":1586215246607,"modified":1586215246607,"name":"Default Jar","parentId":"wrk_31b0b95dd0db41dcbbd866132bb9e4fd","_type":"cookie_jar"}]}